README.rst
setup.py
test/test_core.py
tokit/__init__.py
tokit/api.py
tokit/cassandra.py
tokit/compiler.py
tokit/fabfile.py
tokit/postgres.py
tokit/tasks.py
tokit/traceback.py
tokit/translation.py
tokit/utils.py
tokit.egg-info/PKG-INFO
tokit.egg-info/SOURCES.txt
tokit.egg-info/dependency_links.txt
tokit.egg-info/requires.txt
tokit.egg-info/top_level.txt
tokit/js/babel.js
tokit/js/coffee-script.js
tokit/js/riot-compiler.js
tokit/js/stylus.js