Metadata-Version: 1.1
Name: tokit
Version: 0.7.2
Summary: A kit for development with Tornado web framework
Home-page: https://github.com/manhg/tokit
Author: Giang Manh
Author-email: manhgd@yahoo.com
License: UNKNOWN
Download-URL: https://github.com/manhg/tokit/tarball/0.7.2
Keywords: tornado,web,tokit
Platform: UNKNOWN
Classifier: Programming Language :: Python :: 3.6
